unstract/sdk/__init__.py
unstract/sdk/adapter.py
unstract/sdk/audit.py
unstract/sdk/cache.py
unstract/sdk/constants.py
unstract/sdk/embedding.py
unstract/sdk/exceptions.py
unstract/sdk/helper.py
unstract/sdk/index.py
unstract/sdk/llm.py
unstract/sdk/metrics_mixin.py
unstract/sdk/ocr.py
unstract/sdk/platform.py
unstract/sdk/prompt.py
unstract/sdk/vector_db.py
unstract/sdk/x2txt.py
unstract/sdk/adapters/__init__.py
unstract/sdk/adapters/adapterkit.py
unstract/sdk/adapters/base.py
unstract/sdk/adapters/constants.py
unstract/sdk/adapters/enums.py
unstract/sdk/adapters/exceptions.py
unstract/sdk/adapters/registry.py
unstract/sdk/adapters/utils.py
unstract/sdk/adapters/embedding/__init__.py
unstract/sdk/adapters/embedding/embedding_adapter.py
unstract/sdk/adapters/embedding/helper.py
unstract/sdk/adapters/embedding/register.py
unstract/sdk/adapters/embedding/azure_open_ai/README.md
unstract/sdk/adapters/embedding/azure_open_ai/pyproject.toml
unstract/sdk/adapters/embedding/azure_open_ai/src/__init__.py
unstract/sdk/adapters/embedding/azure_open_ai/src/azure_open_ai.py
unstract/sdk/adapters/embedding/azure_open_ai/src/static/json_schema.json
unstract/sdk/adapters/embedding/bedrock/README.md
unstract/sdk/adapters/embedding/bedrock/pyproject.toml
unstract/sdk/adapters/embedding/bedrock/src/__init__.py
unstract/sdk/adapters/embedding/bedrock/src/bedrock.py
unstract/sdk/adapters/embedding/bedrock/src/static/json_schema.json
unstract/sdk/adapters/embedding/hugging_face/README.md
unstract/sdk/adapters/embedding/hugging_face/pyproject.toml
unstract/sdk/adapters/embedding/hugging_face/src/__init__.py
unstract/sdk/adapters/embedding/hugging_face/src/hugging_face.py
unstract/sdk/adapters/embedding/hugging_face/src/static/json_schema.json
unstract/sdk/adapters/embedding/no_op/README.md
unstract/sdk/adapters/embedding/no_op/pyproject.toml
unstract/sdk/adapters/embedding/no_op/src/__init__.py
unstract/sdk/adapters/embedding/no_op/src/no_op_custom_embedding.py
unstract_sdk-0.79.0.dist-info/METADATA
unstract_sdk-0.79.0.dist-info/WHEEL
unstract_sdk-0.79.0.dist-info/entry_points.txt
unstract_sdk-0.79.0.dist-info/licenses/LICENSE
unstract_sdk-0.79.0.dist-info/RECORD
