Metadata-Version: 2.4
Name: unstract-sdk
Version: 0.79.0
Summary: A framework for writing Unstract Tools/Apps
Project-URL: Homepage, https://unstract.com
Project-URL: Release notes, https://github.com/Zipstack/unstract-sdk/releases
Project-URL: Source, https://github.com/Zipstack/unstract-sdk
Author-email: Zipstack Inc <devsupport@zipstack.com>
License: AGPL v3
License-File: LICENSE
Keywords: unstract tools-development-kit apps development-kit sdk
Classifier: Development Status :: 4 - Beta
Classifier: Intended Audience :: Developers
Classifier: License :: OSI Approved :: GNU Affero General Public License v3
Classifier: Operating System :: MacOS :: MacOS X
Classifier: Operating System :: POSIX :: Linux
Classifier: Programming Language :: Python
Classifier: Programming Language :: Python :: 3.9
Classifier: Topic :: Scientific/Engineering
Classifier: Topic :: Software Development :: Libraries :: Python Modules
Requires-Python: <3.13,>=3.12
Requires-Dist: filetype~=1.2.0
Requires-Dist: httpx>=0.25.2
Requires-Dist: jsonschema<5.0,>=4.18.6
Requires-Dist: llama-index-embeddings-azure-openai==0.4.0
Requires-Dist: llama-index-embeddings-bedrock==0.6.1
Requires-Dist: llama-index-embeddings-google==0.4.0
Requires-Dist: llama-index-embeddings-ollama==0.8.1
Requires-Dist: llama-index-embeddings-openai==0.5.0
Requires-Dist: llama-index-embeddings-vertex==0.4.0
Requires-Dist: llama-index-llms-anthropic==0.8.5
Requires-Dist: llama-index-llms-anyscale==0.4.0
Requires-Dist: llama-index-llms-azure-openai==0.4.0
Requires-Dist: llama-index-llms-bedrock-converse==0.8.2
Requires-Dist: llama-index-llms-mistralai==0.7.0
Requires-Dist: llama-index-llms-ollama==0.7.1
Requires-Dist: llama-index-llms-openai==0.5.4
Requires-Dist: llama-index-llms-palm==0.4.0
Requires-Dist: llama-index-llms-replicate==0.5.0
Requires-Dist: llama-index-llms-vertex==0.6.0
Requires-Dist: llama-index-vector-stores-milvus==0.9.0
Requires-Dist: llama-index-vector-stores-pinecone==0.7.0
Requires-Dist: llama-index-vector-stores-postgres==0.6.3
Requires-Dist: llama-index-vector-stores-qdrant==0.7.1
Requires-Dist: llama-index-vector-stores-weaviate==1.4.0
Requires-Dist: llama-index==0.13.2
Requires-Dist: llama-parse==0.5.19
Requires-Dist: llmwhisperer-client>=2.5.0
Requires-Dist: mistralai==1.9.7
Requires-Dist: pdfplumber>=0.11.2
Requires-Dist: python-dotenv==1.0.1
Requires-Dist: python-magic~=0.4.27
Requires-Dist: redis>=5.2.1
Requires-Dist: singleton-decorator~=1.0.0
Requires-Dist: tiktoken~=0.9.0
Requires-Dist: transformers==4.37.0
Provides-Extra: aws
Requires-Dist: boto3~=1.34.131; extra == 'aws'
Requires-Dist: s3fs[boto3]~=2024.10.0; extra == 'aws'
Provides-Extra: azure
Requires-Dist: adlfs~=2024.7.0; extra == 'azure'
Provides-Extra: gcs
Requires-Dist: gcsfs~=2024.10.0; extra == 'gcs'
